yaqd_new_era/VERSION
yaqd_new_era/__init__.py
yaqd_new_era/__version__.py
yaqd_new_era/_new_era_continuous_nextgen.py
yaqd_new_era/_new_era_ne1000.py
yaqd_new_era/new-era-continuous-nextgen.avpr
yaqd_new_era/new-era-continuous-nextgen.toml
yaqd_new_era/new-era-ne1000.avpr
yaqd_new_era/new-era-ne1000.toml
yaqd_new_era-2022.1.0.dist-info/entry_points.txt
yaqd_new_era-2022.1.0.dist-info/LICENSE
yaqd_new_era-2022.1.0.dist-info/WHEEL
yaqd_new_era-2022.1.0.dist-info/METADATA
yaqd_new_era-2022.1.0.dist-info/RECORD
