Metadata-Version: 2.1
Name: yaqd-new-era
Version: 2022.1.0
Summary: yaq daemons for new era pump systems hardware
Home-page: https://yaq.fyi
Author: Blaise Thompson
Author-email: blaise@untzag.com
Requires-Python: >=3.7
Classifier: Development Status :: 2 - Pre-Alpha
Classifier: Intended Audience :: Science/Research
Classifier: License :: OSI Approved :: GNU Lesser General Public License v3 (LGPLv3)
Classifier: Natural Language :: English
Classifier: Programming Language :: Python :: 3
Classifier: Programming Language :: Python :: 3.7
Classifier: Programming Language :: Python :: 3.8
Classifier: Topic :: Scientific/Engineering
Requires-Dist: yaqd-core>=2020.06.3
Requires-Dist: pyserial
Requires-Dist: black ; extra == "dev"
Requires-Dist: pre-commit ; extra == "dev"
Project-URL: Issues, https://gitlab.com/yaq/yaqd-new-era/issues
Project-URL: Source, https://gitlab.com/yaq/yaqd-new-era
Provides-Extra: dev
